beatrice/__init__.py
beatrice/main.py
beatrice-0.1.5a0.dist-info/METADATA
beatrice-0.1.5a0.dist-info/RECORD
beatrice-0.1.5a0.dist-info/WHEEL
beatrice-0.1.5a0.dist-info/top_level.txt
